pycziutils/__init__.py
pycziutils/_parsers.py
pycziutils/_readers.py
pycziutils-0.3.2.dist-info/LICENSE
pycziutils-0.3.2.dist-info/WHEEL
pycziutils-0.3.2.dist-info/METADATA
pycziutils-0.3.2.dist-info/RECORD
