Metadata-Version: 2.1
Name: pycziutils
Version: 0.3.2
Summary: Python utilities to read CZI files and parse metadata through python-bioformats
Home-page: https://pycziutils.readthedocs.io
License: BSD license
Author: Yohsuke T. Fukai
Author-email: ysk@yfukai.net
Requires-Python: >=3.7.1,<4.0.0
Classifier: Development Status :: 3 - Alpha
Classifier: Intended Audience :: Developers
Classifier: Intended Audience :: Science/Research
Classifier: License :: OSI Approved :: BSD License
Classifier: License :: Other/Proprietary License
Classifier: Natural Language :: English
Classifier: Programming Language :: Python :: 3
Classifier: Programming Language :: Python :: 3.7
Classifier: Programming Language :: Python :: 3.8
Classifier: Programming Language :: Python :: 3.9
Requires-Dist: numpy (>=1.9,<2.0)
Requires-Dist: pandas (>=1.0,<2.0)
Requires-Dist: pydantic (>=1.8.2,<2.0.0)
Requires-Dist: python-bioformats (>=4.0.4,<5.0.0)
Requires-Dist: python-javabridge (>=4.0.3,<5.0.0)
Requires-Dist: xmltodict (>=0.12,<0.13)
Project-URL: Repository, https://github.com/yfukai/pycziutils
